uconst/__init__.py
uconst/__version__.py
uconst/const.py
uconst/constructor.py
uconst-1.0.2.dist-info/METADATA
uconst-1.0.2.dist-info/WHEEL
uconst-1.0.2.dist-info/RECORD
