Metadata-Version: 2.1
Name: uconst
Version: 1.0.2
Summary: 
Author: Robert Stoul
Author-email: rekiiky@proton.me
Requires-Python: >=3.11,<4.0
Classifier: Programming Language :: Python :: 3
Classifier: Programming Language :: Python :: 3.11
Requires-Dist: urllib3 (>=2.0.7,<3.0.0)
